spmac/__init__.py
spmac/main.py
spmac/matsubara.py
spmac/mpi.py
spmac/pade.py
spmac/solver/__init__.py
spmac/solver/base.py
spmac/solver/multiple.py
spmac/solver/pade.py
spmac/solver/single.py
spmac/util.py
pyspmac-0.1.dist-info/LICENSE
pyspmac-0.1.dist-info/METADATA
pyspmac-0.1.dist-info/WHEEL
pyspmac-0.1.dist-info/entry_points.txt
pyspmac-0.1.dist-info/RECORD
