Metadata-Version: 2.1
Name: pySpMAC
Version: 0.1
Summary: spmac
Home-page: https://github.com/SpM-lab/pySpMAC
License: MPL-2.0
Author: Yuichi Motoyama
Author-email: y-motoyama@issp.u-tokyo.ac.jp
Requires-Python: >=3.8
Classifier: License :: OSI Approved
Classifier: Programming Language :: Python :: 3
Classifier: Programming Language :: Python :: 3.8
Classifier: Programming Language :: Python :: 3.9
Classifier: Programming Language :: Python :: 3.10
Classifier: Programming Language :: Python :: 3.11
Classifier: Programming Language :: Python :: 3.12
Requires-Dist: admmsolver (>=0.7.7,<0.8.0)
Requires-Dist: numpy (>=1.21.4,<2.0.0)
Requires-Dist: sparse-ir[xprec] (>=0.92.0,<0.93.0)
Requires-Dist: toml (>=0.10.2,<0.11.0)
Project-URL: Repository, https://github.com/SpM-lab/pySpMAC
